Metadata-Version: 2.1
Name: easypyxl
Version: 0.6.5
Summary: UNKNOWN
Home-page: https://github.com/CauchyComplete/EasyPyXL
Author: CauchyComplete
Author-email: corundum240@gmail.com
License: MIT
Platform: UNKNOWN
License-File: LICENSE
